deepcrawl_robots/__init__.py
deepcrawl_robots/main
deepcrawl_robots/main.py
deepcrawl_robots-0.0.5.dist-info/LICENSE
deepcrawl_robots-0.0.5.dist-info/METADATA
deepcrawl_robots-0.0.5.dist-info/WHEEL
deepcrawl_robots-0.0.5.dist-info/top_level.txt
deepcrawl_robots-0.0.5.dist-info/RECORD
